{
  "language": "cpp",
  "period": "daily",
  "fetch_time": "2025-07-04 01:16:00",
  "repositories": [
    {
      "author": "LadybirdBrowser",
      "name": "ladybird",
      "full_name": "LadybirdBrowser/ladybird",
      "url": "https://github.com/LadybirdBrowser/ladybird",
      "description": "Truly independent web browser",
      "language": "C++",
      "stars": "44508",
      "forks": "1900",
      "today_stars": "198 stars today"
    },
    {
      "author": "protocolbuffers",
      "name": "protobuf",
      "full_name": "protocolbuffers/protobuf",
      "url": "https://github.com/protocolbuffers/protobuf",
      "description": "Protocol Buffers - Google's data interchange format",
      "language": "C++",
      "stars": "67907",
      "forks": "15755",
      "today_stars": "9 stars today"
    },
    {
      "author": "microsoft",
      "name": "onnxruntime",
      "full_name": "microsoft/onnxruntime",
      "url": "https://github.com/microsoft/onnxruntime",
      "description": "ONNX Runtime: cross-platform, high performance ML inferencing and training accelerator",
      "language": "C++",
      "stars": "17092",
      "forks": "3317",
      "today_stars": "6 stars today"
    },
    {
      "author": "ros-navigation",
      "name": "navigation2",
      "full_name": "ros-navigation/navigation2",
      "url": "https://github.com/ros-navigation/navigation2",
      "description": "ROS 2 Navigation Framework and System",
      "language": "C++",
      "stars": "3239",
      "forks": "1498",
      "today_stars": "5 stars today"
    },
    {
      "author": "google",
      "name": "perfetto",
      "full_name": "google/perfetto",
      "url": "https://github.com/google/perfetto",
      "description": "Production-grade client-side tracing, profiling, and analysis for complex software systems.",
      "language": "C++",
      "stars": "4178",
      "forks": "503",
      "today_stars": "2 stars today"
    },
    {
      "author": "bytedance",
      "name": "btrace",
      "full_name": "bytedance/btrace",
      "url": "https://github.com/bytedance/btrace",
      "description": "🔥🔥 btrace (AKA RheaTrace) is a high-performance Android & iOS tracing tool built on Perfetto. It not only times your methods but also reveals why they’re slow.",
      "language": "C++",
      "stars": "2228",
      "forks": "302",
      "today_stars": "30 stars today"
    },
    {
      "author": "topling",
      "name": "toplingdb",
      "full_name": "topling/toplingdb",
      "url": "https://github.com/topling/toplingdb",
      "description": "ToplingDB is a cloud native LSM Key-Value Store with searchable compression algo and distributed compaction",
      "language": "C++",
      "stars": "964",
      "forks": "147",
      "today_stars": "26 stars today"
    },
    {
      "author": "deskflow",
      "name": "deskflow",
      "full_name": "deskflow/deskflow",
      "url": "https://github.com/deskflow/deskflow",
      "description": "Share a single keyboard and mouse between multiple computers.",
      "language": "C++",
      "stars": "18626",
      "forks": "4078",
      "today_stars": "20 stars today"
    },
    {
      "author": "swiftlang",
      "name": "swift",
      "full_name": "swiftlang/swift",
      "url": "https://github.com/swiftlang/swift",
      "description": "The Swift Programming Language",
      "language": "C++",
      "stars": "68787",
      "forks": "10496",
      "today_stars": "11 stars today"
    },
    {
      "author": "NVIDIA",
      "name": "nccl",
      "full_name": "NVIDIA/nccl",
      "url": "https://github.com/NVIDIA/nccl",
      "description": "Optimized primitives for collective multi-GPU communication",
      "language": "C++",
      "stars": "3834",
      "forks": "950",
      "today_stars": "1 star today"
    },
    {
      "author": "k2-fsa",
      "name": "sherpa-onnx",
      "full_name": "k2-fsa/sherpa-onnx",
      "url": "https://github.com/k2-fsa/sherpa-onnx",
      "description": "Speech-to-text, text-to-speech, speaker diarization, speech enhancement, source separation, and VAD using next-gen Kaldi with onnxruntime without Internet connection. Support embedded systems, Android, iOS, HarmonyOS, Raspberry Pi, RISC-V, x86_64 servers, websocket server/client, support 12 programming languages",
      "language": "C++",
      "stars": "6568",
      "forks": "752",
      "today_stars": "13 stars today"
    },
    {
      "author": "facebook",
      "name": "react-native",
      "full_name": "facebook/react-native",
      "url": "https://github.com/facebook/react-native",
      "description": "A framework for building native applications using React",
      "language": "C++",
      "stars": "122897",
      "forks": "24734",
      "today_stars": "19 stars today"
    },
    {
      "author": "fmtlib",
      "name": "fmt",
      "full_name": "fmtlib/fmt",
      "url": "https://github.com/fmtlib/fmt",
      "description": "A modern formatting library",
      "language": "C++",
      "stars": "22014",
      "forks": "2660",
      "today_stars": "8 stars today"
    },
    {
      "author": "tensorflow",
      "name": "tensorflow",
      "full_name": "tensorflow/tensorflow",
      "url": "https://github.com/tensorflow/tensorflow",
      "description": "An Open Source Machine Learning Framework for Everyone",
      "language": "C++",
      "stars": "190556",
      "forks": "74736",
      "today_stars": "23 stars today"
    },
    {
      "author": "nlohmann",
      "name": "json",
      "full_name": "nlohmann/json",
      "url": "https://github.com/nlohmann/json",
      "description": "JSON for Modern C++",
      "language": "C++",
      "stars": "46310",
      "forks": "7041",
      "today_stars": "16 stars today"
    },
    {
      "author": "facebook",
      "name": "folly",
      "full_name": "facebook/folly",
      "url": "https://github.com/facebook/folly",
      "description": "An open-source C++ library developed and used at Facebook.",
      "language": "C++",
      "stars": "29529",
      "forks": "5717",
      "today_stars": "6 stars today"
    },
    {
      "author": "ZLMediaKit",
      "name": "ZLMediaKit",
      "full_name": "ZLMediaKit/ZLMediaKit",
      "url": "https://github.com/ZLMediaKit/ZLMediaKit",
      "description": "WebRTC/RTSP/RTMP/HTTP/HLS/HTTP-FLV/WebSocket-FLV/HTTP-TS/HTTP-fMP4/WebSocket-TS/WebSocket-fMP4/GB28181/SRT server and client framework based on C++11",
      "language": "C++",
      "stars": "15343",
      "forks": "3710",
      "today_stars": "9 stars today"
    },
    {
      "author": "meshtastic",
      "name": "firmware",
      "full_name": "meshtastic/firmware",
      "url": "https://github.com/meshtastic/firmware",
      "description": "The official firmware for Meshtastic, an open-source, off-grid mesh communication system.",
      "language": "C++",
      "stars": "5013",
      "forks": "1309",
      "today_stars": "8 stars today"
    },
    {
      "author": "Tencent",
      "name": "ncnn",
      "full_name": "Tencent/ncnn",
      "url": "https://github.com/Tencent/ncnn",
      "description": "ncnn is a high-performance neural network inference framework optimized for the mobile platform",
      "language": "C++",
      "stars": "21724",
      "forks": "4273",
      "today_stars": "8 stars today"
    },
    {
      "author": "carbon-language",
      "name": "carbon-lang",
      "full_name": "carbon-language/carbon-lang",
      "url": "https://github.com/carbon-language/carbon-lang",
      "description": "Carbon Language's main repository: documents, design, implementation, and related tools. (NOTE: Carbon Language is experimental; see README)",
      "language": "C++",
      "stars": "32978",
      "forks": "1494",
      "today_stars": "6 stars today"
    },
    {
      "author": "ClickHouse",
      "name": "ClickHouse",
      "full_name": "ClickHouse/ClickHouse",
      "url": "https://github.com/ClickHouse/ClickHouse",
      "description": "ClickHouse® is a real-time analytics database management system",
      "language": "C++",
      "stars": "41511",
      "forks": "7445",
      "today_stars": "36 stars today"
    },
    {
      "author": "opencv",
      "name": "opencv",
      "full_name": "opencv/opencv",
      "url": "https://github.com/opencv/opencv",
      "description": "Open Source Computer Vision Library",
      "language": "C++",
      "stars": "82899",
      "forks": "56204",
      "today_stars": "35 stars today"
    },
    {
      "author": "facebookresearch",
      "name": "faiss",
      "full_name": "facebookresearch/faiss",
      "url": "https://github.com/facebookresearch/faiss",
      "description": "A library for efficient similarity search and clustering of dense vectors.",
      "language": "C++",
      "stars": "35865",
      "forks": "3935",
      "today_stars": "31 stars today"
    },
    {
      "author": "espressif",
      "name": "arduino-esp32",
      "full_name": "espressif/arduino-esp32",
      "url": "https://github.com/espressif/arduino-esp32",
      "description": "Arduino core for the ESP32",
      "language": "C++",
      "stars": "15007",
      "forks": "7653",
      "today_stars": "3 stars today"
    }
  ]
}