{
  "language": "go",
  "period": "daily",
  "fetch_time": "2025-04-27 01:14:19",
  "repositories": [
    {
      "author": "aquasecurity",
      "name": "trivy",
      "full_name": "aquasecurity/trivy",
      "url": "https://github.com/aquasecurity/trivy",
      "description": "Find vulnerabilities, misconfigurations, secrets, SBOM in containers, Kubernetes, code repositories, clouds and more",
      "language": "Go",
      "stars": "25843",
      "forks": "2515",
      "today_stars": "145 stars today"
    },
    {
      "author": "nats-io",
      "name": "nats-server",
      "full_name": "nats-io/nats-server",
      "url": "https://github.com/nats-io/nats-server",
      "description": "High-Performance server for NATS.io, the cloud and edge native messaging system.",
      "language": "Go",
      "stars": "16968",
      "forks": "1535",
      "today_stars": "22 stars today"
    },
    {
      "author": "GoogleCloudPlatform",
      "name": "microservices-demo",
      "full_name": "GoogleCloudPlatform/microservices-demo",
      "url": "https://github.com/GoogleCloudPlatform/microservices-demo",
      "description": "Sample cloud-first application with 10 microservices showcasing Kubernetes, Istio, and gRPC.",
      "language": "Go",
      "stars": "17860",
      "forks": "7992",
      "today_stars": "10 stars today"
    },
    {
      "author": "daytonaio",
      "name": "daytona",
      "full_name": "daytonaio/daytona",
      "url": "https://github.com/daytonaio/daytona",
      "description": "Daytona is a Secure and Elastic Infrastructure for Running AI-Generated Code.",
      "language": "Go",
      "stars": "15300",
      "forks": "1394",
      "today_stars": "45 stars today"
    },
    {
      "author": "spf13",
      "name": "cobra",
      "full_name": "spf13/cobra",
      "url": "https://github.com/spf13/cobra",
      "description": "A Commander for modern Go CLI interactions",
      "language": "Go",
      "stars": "40245",
      "forks": "2927",
      "today_stars": "11 stars today"
    },
    {
      "author": "cert-manager",
      "name": "cert-manager",
      "full_name": "cert-manager/cert-manager",
      "url": "https://github.com/cert-manager/cert-manager",
      "description": "Automatically provision and manage TLS certificates in Kubernetes",
      "language": "Go",
      "stars": "12744",
      "forks": "2198",
      "today_stars": "5 stars today"
    },
    {
      "author": "go-playground",
      "name": "validator",
      "full_name": "go-playground/validator",
      "url": "https://github.com/go-playground/validator",
      "description": "💯Go Struct and Field validation, including Cross Field, Cross Struct, Map, Slice and Array diving",
      "language": "Go",
      "stars": "18193",
      "forks": "1366",
      "today_stars": "59 stars today"
    },
    {
      "author": "kubernetes-sigs",
      "name": "external-dns",
      "full_name": "kubernetes-sigs/external-dns",
      "url": "https://github.com/kubernetes-sigs/external-dns",
      "description": "Configure external DNS servers (AWS Route53, Google CloudDNS and others) for Kubernetes Ingresses and Services",
      "language": "Go",
      "stars": "8111",
      "forks": "2666",
      "today_stars": "4 stars today"
    },
    {
      "author": "grpc-ecosystem",
      "name": "grpc-gateway",
      "full_name": "grpc-ecosystem/grpc-gateway",
      "url": "https://github.com/grpc-ecosystem/grpc-gateway",
      "description": "gRPC to JSON proxy generator following the gRPC HTTP spec",
      "language": "Go",
      "stars": "19175",
      "forks": "2309",
      "today_stars": "3 stars today"
    },
    {
      "author": "golang",
      "name": "tools",
      "full_name": "golang/tools",
      "url": "https://github.com/golang/tools",
      "description": "[mirror] Go Tools",
      "language": "Go",
      "stars": "7631",
      "forks": "2295",
      "today_stars": "10 stars today"
    },
    {
      "author": "projectdiscovery",
      "name": "katana",
      "full_name": "projectdiscovery/katana",
      "url": "https://github.com/projectdiscovery/katana",
      "description": "A next-generation crawling and spidering framework.",
      "language": "Go",
      "stars": "13552",
      "forks": "720",
      "today_stars": "38 stars today"
    },
    {
      "author": "coder",
      "name": "coder",
      "full_name": "coder/coder",
      "url": "https://github.com/coder/coder",
      "description": "Provision remote development environments via Terraform",
      "language": "Go",
      "stars": "9632",
      "forks": "862",
      "today_stars": "20 stars today"
    },
    {
      "author": "gofr-dev",
      "name": "gofr",
      "full_name": "gofr-dev/gofr",
      "url": "https://github.com/gofr-dev/gofr",
      "description": "An opinionated GoLang framework for accelerated microservice development. Built in support for databases and observability.",
      "language": "Go",
      "stars": "10173",
      "forks": "1656",
      "today_stars": "352 stars today"
    },
    {
      "author": "hashicorp",
      "name": "packer",
      "full_name": "hashicorp/packer",
      "url": "https://github.com/hashicorp/packer",
      "description": "Packer is a tool for creating identical machine images for multiple platforms from a single source configuration.",
      "language": "Go",
      "stars": "15353",
      "forks": "3337",
      "today_stars": "4 stars today"
    },
    {
      "author": "joho",
      "name": "godotenv",
      "full_name": "joho/godotenv",
      "url": "https://github.com/joho/godotenv",
      "description": "A Go port of Ruby's dotenv library (Loads environment variables from .env files)",
      "language": "Go",
      "stars": "9176",
      "forks": "426",
      "today_stars": "53 stars today"
    },
    {
      "author": "go-gorm",
      "name": "gorm",
      "full_name": "go-gorm/gorm",
      "url": "https://github.com/go-gorm/gorm",
      "description": "The fantastic ORM library for Golang, aims to be developer friendly",
      "language": "Go",
      "stars": "38068",
      "forks": "4000",
      "today_stars": "12 stars today"
    },
    {
      "author": "gravitational",
      "name": "teleport",
      "full_name": "gravitational/teleport",
      "url": "https://github.com/gravitational/teleport",
      "description": "The easiest, and most secure way to access and protect all of your infrastructure.",
      "language": "Go",
      "stars": "18361",
      "forks": "1827",
      "today_stars": "15 stars today"
    },
    {
      "author": "prometheus",
      "name": "node_exporter",
      "full_name": "prometheus/node_exporter",
      "url": "https://github.com/prometheus/node_exporter",
      "description": "Exporter for machine metrics",
      "language": "Go",
      "stars": "11960",
      "forks": "2465",
      "today_stars": "4 stars today"
    },
    {
      "author": "envoyproxy",
      "name": "gateway",
      "full_name": "envoyproxy/gateway",
      "url": "https://github.com/envoyproxy/gateway",
      "description": "Manages Envoy Proxy as a Standalone or Kubernetes-based Application Gateway",
      "language": "Go",
      "stars": "1831",
      "forks": "449",
      "today_stars": "2 stars today"
    },
    {
      "author": "stretchr",
      "name": "testify",
      "full_name": "stretchr/testify",
      "url": "https://github.com/stretchr/testify",
      "description": "A toolkit with common assertions and mocks that plays nicely with the standard library",
      "language": "Go",
      "stars": "24491",
      "forks": "1640",
      "today_stars": "2 stars today"
    },
    {
      "author": "jesseduffield",
      "name": "lazygit",
      "full_name": "jesseduffield/lazygit",
      "url": "https://github.com/jesseduffield/lazygit",
      "description": "simple terminal UI for git commands",
      "language": "Go",
      "stars": "59282",
      "forks": "2030",
      "today_stars": "84 stars today"
    },
    {
      "author": "open-telemetry",
      "name": "opentelemetry-collector",
      "full_name": "open-telemetry/opentelemetry-collector",
      "url": "https://github.com/open-telemetry/opentelemetry-collector",
      "description": "OpenTelemetry Collector",
      "language": "Go",
      "stars": "5108",
      "forks": "1603",
      "today_stars": "5 stars today"
    }
  ]
}