{
  "language": "java",
  "period": "weekly",
  "fetch_time": "2025-05-09 01:12:33",
  "repositories": [
    {
      "author": "LawnchairLauncher",
      "name": "lawnchair",
      "full_name": "LawnchairLauncher/lawnchair",
      "url": "https://github.com/LawnchairLauncher/lawnchair",
      "description": "No clever tagline needed.",
      "language": "Java",
      "stars": "10220",
      "forks": "1290",
      "today_stars": "63 stars this week"
    },
    {
      "author": "iluwatar",
      "name": "java-design-patterns",
      "full_name": "iluwatar/java-design-patterns",
      "url": "https://github.com/iluwatar/java-design-patterns",
      "description": "Design patterns implemented in Java",
      "language": "Java",
      "stars": "91652",
      "forks": "26967",
      "today_stars": "236 stars this week"
    },
    {
      "author": "TeamNewPipe",
      "name": "NewPipe",
      "full_name": "TeamNewPipe/NewPipe",
      "url": "https://github.com/TeamNewPipe/NewPipe",
      "description": "A libre lightweight streaming front-end for Android.",
      "language": "Java",
      "stars": "33755",
      "forks": "3192",
      "today_stars": "124 stars this week"
    },
    {
      "author": "Stirling-Tools",
      "name": "Stirling-PDF",
      "full_name": "Stirling-Tools/Stirling-PDF",
      "url": "https://github.com/Stirling-Tools/Stirling-PDF",
      "description": "#1 Locally hosted web application that allows you to perform various operations on PDF files",
      "language": "Java",
      "stars": "58139",
      "forks": "4868",
      "today_stars": "834 stars this week"
    },
    {
      "author": "aws",
      "name": "aws-sdk-java-v2",
      "full_name": "aws/aws-sdk-java-v2",
      "url": "https://github.com/aws/aws-sdk-java-v2",
      "description": "The official AWS SDK for Java - Version 2",
      "language": "Java",
      "stars": "2382",
      "forks": "907",
      "today_stars": "89 stars this week"
    },
    {
      "author": "conductor-oss",
      "name": "conductor",
      "full_name": "conductor-oss/conductor",
      "url": "https://github.com/conductor-oss/conductor",
      "description": "Conductor is an event driven orchestration platform providing durable and highly resilient execution engine for your applications",
      "language": "Java",
      "stars": "22034",
      "forks": "598",
      "today_stars": "742 stars this week"
    },
    {
      "author": "yuliskov",
      "name": "SmartTube",
      "full_name": "yuliskov/SmartTube",
      "url": "https://github.com/yuliskov/SmartTube",
      "description": "Advanced player for set-top boxes and tvs running Android OS",
      "language": "Java",
      "stars": "22576",
      "forks": "1205",
      "today_stars": "124 stars this week"
    },
    {
      "author": "quarkusio",
      "name": "quarkus",
      "full_name": "quarkusio/quarkus",
      "url": "https://github.com/quarkusio/quarkus",
      "description": "Quarkus: Supersonic Subatomic Java.",
      "language": "Java",
      "stars": "14485",
      "forks": "2840",
      "today_stars": "81 stars this week"
    },
    {
      "author": "hkhcoder",
      "name": "vprofile-project",
      "full_name": "hkhcoder/vprofile-project",
      "url": "https://github.com/hkhcoder/vprofile-project",
      "description": "",
      "language": "Java",
      "stars": "593",
      "forks": "2831",
      "today_stars": "24 stars this week"
    },
    {
      "author": "ashishps1",
      "name": "awesome-leetcode-resources",
      "full_name": "ashishps1/awesome-leetcode-resources",
      "url": "https://github.com/ashishps1/awesome-leetcode-resources",
      "description": "Awesome LeetCode resources to learn Data Structures and Algorithms and prepare for Coding Interviews.",
      "language": "Java",
      "stars": "10054",
      "forks": "2367",
      "today_stars": "222 stars this week"
    },
    {
      "author": "keycloak",
      "name": "keycloak",
      "full_name": "keycloak/keycloak",
      "url": "https://github.com/keycloak/keycloak",
      "description": "Open Source Identity and Access Management For Modern Applications and Services",
      "language": "Java",
      "stars": "27060",
      "forks": "7269",
      "today_stars": "148 stars this week"
    },
    {
      "author": "aeron-io",
      "name": "aeron",
      "full_name": "aeron-io/aeron",
      "url": "https://github.com/aeron-io/aeron",
      "description": "Efficient reliable UDP unicast, UDP multicast, and IPC message transport",
      "language": "Java",
      "stars": "7736",
      "forks": "924",
      "today_stars": "17 stars this week"
    },
    {
      "author": "spring-projects",
      "name": "spring-boot",
      "full_name": "spring-projects/spring-boot",
      "url": "https://github.com/spring-projects/spring-boot",
      "description": "Spring Boot helps you to create Spring-powered, production-grade applications and services with absolute minimum fuss.",
      "language": "Java",
      "stars": "77061",
      "forks": "41155",
      "today_stars": "109 stars this week"
    },
    {
      "author": "apache",
      "name": "beam",
      "full_name": "apache/beam",
      "url": "https://github.com/apache/beam",
      "description": "Apache Beam is a unified programming model for Batch and Streaming data processing.",
      "language": "Java",
      "stars": "8090",
      "forks": "4328",
      "today_stars": "9 stars this week"
    },
    {
      "author": "zxing",
      "name": "zxing",
      "full_name": "zxing/zxing",
      "url": "https://github.com/zxing/zxing",
      "description": "ZXing (\"Zebra Crossing\") barcode scanning library for Java, Android",
      "language": "Java",
      "stars": "33295",
      "forks": "9404",
      "today_stars": "32 stars this week"
    },
    {
      "author": "runelite",
      "name": "runelite",
      "full_name": "runelite/runelite",
      "url": "https://github.com/runelite/runelite",
      "description": "Open source Old School RuneScape client",
      "language": "Java",
      "stars": "4980",
      "forks": "5359",
      "today_stars": "8 stars this week"
    },
    {
      "author": "PaperMC",
      "name": "Paper",
      "full_name": "PaperMC/Paper",
      "url": "https://github.com/PaperMC/Paper",
      "description": "The most widely used, high performance Minecraft server that aims to fix gameplay and mechanics inconsistencies",
      "language": "Java",
      "stars": "10990",
      "forks": "2537",
      "today_stars": "72 stars this week"
    },
    {
      "author": "Dev4Mod",
      "name": "WaEnhancer",
      "full_name": "Dev4Mod/WaEnhancer",
      "url": "https://github.com/Dev4Mod/WaEnhancer",
      "description": "WhatsApp tools for Android",
      "language": "Java",
      "stars": "743",
      "forks": "98",
      "today_stars": "19 stars this week"
    },
    {
      "author": "kunal-kushwaha",
      "name": "DSA-Bootcamp-Java",
      "full_name": "kunal-kushwaha/DSA-Bootcamp-Java",
      "url": "https://github.com/kunal-kushwaha/DSA-Bootcamp-Java",
      "description": "This repository consists of the code samples, assignments, and notes for the Java data structures & algorithms + interview preparation bootcamp of WeMakeDevs.",
      "language": "Java",
      "stars": "18955",
      "forks": "11914",
      "today_stars": "62 stars this week"
    },
    {
      "author": "jhy",
      "name": "jsoup",
      "full_name": "jhy/jsoup",
      "url": "https://github.com/jhy/jsoup",
      "description": "jsoup: the Java HTML parser, built for HTML editing, cleaning, scraping, and XSS safety.",
      "language": "Java",
      "stars": "11150",
      "forks": "2229",
      "today_stars": "19 stars this week"
    },
    {
      "author": "questdb",
      "name": "questdb",
      "full_name": "questdb/questdb",
      "url": "https://github.com/questdb/questdb",
      "description": "QuestDB is a high performance, open-source, time-series database",
      "language": "Java",
      "stars": "15144",
      "forks": "1237",
      "today_stars": "25 stars this week"
    },
    {
      "author": "vespa-engine",
      "name": "vespa",
      "full_name": "vespa-engine/vespa",
      "url": "https://github.com/vespa-engine/vespa",
      "description": "AI + Data, online. https://vespa.ai",
      "language": "Java",
      "stars": "6156",
      "forks": "632",
      "today_stars": "15 stars this week"
    }
  ]
}