{
  "language": "swift",
  "period": "daily",
  "fetch_time": "2025-06-06 01:15:54",
  "repositories": [
    {
      "author": "vapor",
      "name": "vapor",
      "full_name": "vapor/vapor",
      "url": "https://github.com/vapor/vapor",
      "description": "💧 A server-side Swift HTTP web framework.",
      "language": "Swift",
      "stars": "25177",
      "forks": "1482",
      "today_stars": "14 stars today"
    },
    {
      "author": "apple",
      "name": "swift-nio",
      "full_name": "apple/swift-nio",
      "url": "https://github.com/apple/swift-nio",
      "description": "Event-driven network application framework for high performance protocol servers & clients, non-blocking.",
      "language": "Swift",
      "stars": "8154",
      "forks": "674",
      "today_stars": "6 stars today"
    },
    {
      "author": "siteline",
      "name": "swiftui-introspect",
      "full_name": "siteline/swiftui-introspect",
      "url": "https://github.com/siteline/swiftui-introspect",
      "description": "Introspect underlying UIKit/AppKit components from SwiftUI",
      "language": "Swift",
      "stars": "6083",
      "forks": "368",
      "today_stars": "4 stars today"
    },
    {
      "author": "mrousavy",
      "name": "react-native-vision-camera",
      "full_name": "mrousavy/react-native-vision-camera",
      "url": "https://github.com/mrousavy/react-native-vision-camera",
      "description": "📸 A powerful, high-performance React Native Camera library.",
      "language": "Swift",
      "stars": "8455",
      "forks": "1204",
      "today_stars": "3 stars today"
    },
    {
      "author": "github",
      "name": "CopilotForXcode",
      "full_name": "github/CopilotForXcode",
      "url": "https://github.com/github/CopilotForXcode",
      "description": "Xcode extension for GitHub Copilot",
      "language": "Swift",
      "stars": "4154",
      "forks": "732",
      "today_stars": "9 stars today"
    },
    {
      "author": "modelcontextprotocol",
      "name": "swift-sdk",
      "full_name": "modelcontextprotocol/swift-sdk",
      "url": "https://github.com/modelcontextprotocol/swift-sdk",
      "description": "The official Swift SDK for Model Context Protocol servers and clients. Maintained in collaboration with @loopwork-ai.",
      "language": "Swift",
      "stars": "668",
      "forks": "69",
      "today_stars": "6 stars today"
    },
    {
      "author": "nicklockwood",
      "name": "SwiftFormat",
      "full_name": "nicklockwood/SwiftFormat",
      "url": "https://github.com/nicklockwood/SwiftFormat",
      "description": "A command-line tool and Xcode Extension for formatting Swift code",
      "language": "Swift",
      "stars": "8306",
      "forks": "644",
      "today_stars": "1 star today"
    },
    {
      "author": "stackotter",
      "name": "swift-cross-ui",
      "full_name": "stackotter/swift-cross-ui",
      "url": "https://github.com/stackotter/swift-cross-ui",
      "description": "A cross-platform declarative UI framework, inspired by SwiftUI.",
      "language": "Swift",
      "stars": "1008",
      "forks": "48",
      "today_stars": "9 stars today"
    },
    {
      "author": "gonzalezreal",
      "name": "swift-markdown-ui",
      "full_name": "gonzalezreal/swift-markdown-ui",
      "url": "https://github.com/gonzalezreal/swift-markdown-ui",
      "description": "Display and customize Markdown text in SwiftUI",
      "language": "Swift",
      "stars": "3226",
      "forks": "416",
      "today_stars": "6 stars today"
    },
    {
      "author": "getsentry",
      "name": "sentry-cocoa",
      "full_name": "getsentry/sentry-cocoa",
      "url": "https://github.com/getsentry/sentry-cocoa",
      "description": "The official Sentry SDK for iOS, tvOS, macOS, watchOS.",
      "language": "Swift",
      "stars": "910",
      "forks": "356",
      "today_stars": "0 stars today"
    },
    {
      "author": "swiftlang",
      "name": "swift-syntax",
      "full_name": "swiftlang/swift-syntax",
      "url": "https://github.com/swiftlang/swift-syntax",
      "description": "A set of Swift libraries for parsing, inspecting, generating, and transforming Swift source code.",
      "language": "Swift",
      "stars": "3437",
      "forks": "440",
      "today_stars": "1 star today"
    },
    {
      "author": "apple",
      "name": "swift-collections",
      "full_name": "apple/swift-collections",
      "url": "https://github.com/apple/swift-collections",
      "description": "Commonly used data structures for Swift",
      "language": "Swift",
      "stars": "4054",
      "forks": "330",
      "today_stars": "3 stars today"
    },
    {
      "author": "quoid",
      "name": "userscripts",
      "full_name": "quoid/userscripts",
      "url": "https://github.com/quoid/userscripts",
      "description": "An open-source userscript manager for Safari",
      "language": "Swift",
      "stars": "3743",
      "forks": "257",
      "today_stars": "2 stars today"
    },
    {
      "author": "pointfreeco",
      "name": "swift-snapshot-testing",
      "full_name": "pointfreeco/swift-snapshot-testing",
      "url": "https://github.com/pointfreeco/swift-snapshot-testing",
      "description": "📸 Delightful Swift snapshot testing.",
      "language": "Swift",
      "stars": "3947",
      "forks": "612",
      "today_stars": "2 stars today"
    },
    {
      "author": "realm",
      "name": "SwiftLint",
      "full_name": "realm/SwiftLint",
      "url": "https://github.com/realm/SwiftLint",
      "description": "A tool to enforce Swift style and conventions.",
      "language": "Swift",
      "stars": "19011",
      "forks": "2251",
      "today_stars": "2 stars today"
    },
    {
      "author": "whoeevee",
      "name": "EeveeSpotify",
      "full_name": "whoeevee/EeveeSpotify",
      "url": "https://github.com/whoeevee/EeveeSpotify",
      "description": "A tweak to get Spotify Premium for free, just like Spotilife",
      "language": "Swift",
      "stars": "5344",
      "forks": "428",
      "today_stars": "10 stars today"
    },
    {
      "author": "rxhanson",
      "name": "Rectangle",
      "full_name": "rxhanson/Rectangle",
      "url": "https://github.com/rxhanson/Rectangle",
      "description": "Move and resize windows on macOS with keyboard shortcuts and snap areas",
      "language": "Swift",
      "stars": "27036",
      "forks": "822",
      "today_stars": "19 stars today"
    },
    {
      "author": "apollographql",
      "name": "apollo-ios",
      "full_name": "apollographql/apollo-ios",
      "url": "https://github.com/apollographql/apollo-ios",
      "description": "📱  A strongly-typed, caching GraphQL client for iOS, written in Swift.",
      "language": "Swift",
      "stars": "3948",
      "forks": "749",
      "today_stars": "1 star today"
    }
  ]
}