{
  "language": "php",
  "period": "daily",
  "fetch_time": "2025-04-09 01:10:28",
  "repositories": [
    {
      "author": "nextcloud",
      "name": "all-in-one",
      "full_name": "nextcloud/all-in-one",
      "url": "https://github.com/nextcloud/all-in-one",
      "description": "📦 The official Nextcloud installation method. Provides easy deployment and maintenance with most features included in this one Nextcloud instance.",
      "language": "PHP",
      "stars": "6513",
      "forks": "741",
      "today_stars": "10 stars today"
    },
    {
      "author": "filamentphp",
      "name": "filament",
      "full_name": "filamentphp/filament",
      "url": "https://github.com/filamentphp/filament",
      "description": "A collection of beautiful full-stack components for Laravel. The perfect starting point for your next app. Using Livewire, Alpine.js and Tailwind CSS.",
      "language": "PHP",
      "stars": "22570",
      "forks": "3330",
      "today_stars": "33 stars today"
    },
    {
      "author": "digininja",
      "name": "DVWA",
      "full_name": "digininja/DVWA",
      "url": "https://github.com/digininja/DVWA",
      "description": "Damn Vulnerable Web Application (DVWA)",
      "language": "PHP",
      "stars": "10976",
      "forks": "3903",
      "today_stars": "6 stars today"
    },
    {
      "author": "Dolibarr",
      "name": "dolibarr",
      "full_name": "Dolibarr/dolibarr",
      "url": "https://github.com/Dolibarr/dolibarr",
      "description": "Dolibarr ERP CRM is a modern software package to manage your company or foundation's activity (contacts, suppliers, invoices, orders, stocks, agenda, accounting, ...). it's an open source Web application (written in PHP) designed for businesses of any sizes, foundations and freelancers.",
      "language": "PHP",
      "stars": "5890",
      "forks": "2914",
      "today_stars": "3 stars today"
    },
    {
      "author": "matomo-org",
      "name": "matomo",
      "full_name": "matomo-org/matomo",
      "url": "https://github.com/matomo-org/matomo",
      "description": "Empowering People Ethically 🚀 — Matomo is hiring! Join us → https://matomo.org/jobs Matomo is the leading open-source alternative to Google Analytics, giving you complete control and built-in privacy. Easily collect, visualise, and analyse data from websites & apps. Star us on GitHub ⭐️ – Pull Requests welcome!",
      "language": "PHP",
      "stars": "20392",
      "forks": "2700",
      "today_stars": "4 stars today"
    },
    {
      "author": "leokhoa",
      "name": "laragon",
      "full_name": "leokhoa/laragon",
      "url": "https://github.com/leokhoa/laragon",
      "description": "Laragon is a portable, isolated, fast & powerful universal development environment for PHP, Node.js, Python. It is fast, lightweight, easy-to-use and easy-to-extend.",
      "language": "PHP",
      "stars": "4856",
      "forks": "417",
      "today_stars": "1 star today"
    },
    {
      "author": "SpartnerNL",
      "name": "Laravel-Excel",
      "full_name": "SpartnerNL/Laravel-Excel",
      "url": "https://github.com/SpartnerNL/Laravel-Excel",
      "description": "🚀 Supercharged Excel exports and imports in Laravel",
      "language": "PHP",
      "stars": "12458",
      "forks": "1939",
      "today_stars": "4 stars today"
    },
    {
      "author": "magento",
      "name": "magento2",
      "full_name": "magento/magento2",
      "url": "https://github.com/magento/magento2",
      "description": "Prior to making any Submission(s), you must sign an Adobe Contributor License Agreement, available here at: https://opensource.adobe.com/cla.html. All Submissions you make to Adobe Inc. and its affiliates, assigns and subsidiaries (collectively “Adobe”) are subject to the terms of the Adobe Contributor License Agreement.",
      "language": "PHP",
      "stars": "11762",
      "forks": "9360",
      "today_stars": "3 stars today"
    },
    {
      "author": "PHPOffice",
      "name": "PhpSpreadsheet",
      "full_name": "PHPOffice/PhpSpreadsheet",
      "url": "https://github.com/PHPOffice/PhpSpreadsheet",
      "description": "A pure PHP library for reading and writing spreadsheet files",
      "language": "PHP",
      "stars": "13581",
      "forks": "3546",
      "today_stars": "1 star today"
    },
    {
      "author": "composer",
      "name": "composer",
      "full_name": "composer/composer",
      "url": "https://github.com/composer/composer",
      "description": "Dependency Manager for PHP",
      "language": "PHP",
      "stars": "28917",
      "forks": "4611",
      "today_stars": "2 stars today"
    },
    {
      "author": "BookStackApp",
      "name": "BookStack",
      "full_name": "BookStackApp/BookStack",
      "url": "https://github.com/BookStackApp/BookStack",
      "description": "A platform to create documentation/wiki content built with PHP & Laravel",
      "language": "PHP",
      "stars": "16380",
      "forks": "2040",
      "today_stars": "7 stars today"
    },
    {
      "author": "shopware",
      "name": "shopware",
      "full_name": "shopware/shopware",
      "url": "https://github.com/shopware/shopware",
      "description": "Shopware 6 is an open commerce platform based on Symfony Framework and Vue and supported by a worldwide community and more than 1.500 community extensions",
      "language": "PHP",
      "stars": "3004",
      "forks": "1067",
      "today_stars": "1 star today"
    },
    {
      "author": "DataDog",
      "name": "dd-trace-php",
      "full_name": "DataDog/dd-trace-php",
      "url": "https://github.com/DataDog/dd-trace-php",
      "description": "Datadog PHP Clients",
      "language": "PHP",
      "stars": "520",
      "forks": "163",
      "today_stars": "0 stars today"
    },
    {
      "author": "statamic",
      "name": "cms",
      "full_name": "statamic/cms",
      "url": "https://github.com/statamic/cms",
      "description": "The core Laravel CMS Composer package",
      "language": "PHP",
      "stars": "4334",
      "forks": "566",
      "today_stars": "3 stars today"
    },
    {
      "author": "firefly-iii",
      "name": "firefly-iii",
      "full_name": "firefly-iii/firefly-iii",
      "url": "https://github.com/firefly-iii/firefly-iii",
      "description": "Firefly III: a personal finances manager",
      "language": "PHP",
      "stars": "18640",
      "forks": "1653",
      "today_stars": "9 stars today"
    },
    {
      "author": "woocommerce",
      "name": "woocommerce",
      "full_name": "woocommerce/woocommerce",
      "url": "https://github.com/woocommerce/woocommerce",
      "description": "A customizable, open-source ecommerce platform built on WordPress. Build any commerce solution you can imagine.",
      "language": "PHP",
      "stars": "9680",
      "forks": "10774",
      "today_stars": "2 stars today"
    },
    {
      "author": "pimcore",
      "name": "pimcore",
      "full_name": "pimcore/pimcore",
      "url": "https://github.com/pimcore/pimcore",
      "description": "Core Framework for the Open Source Data & Experience Management Platform (PIM, MDM, CDP, DAM, DXP/CMS & Digital Commerce)",
      "language": "PHP",
      "stars": "3538",
      "forks": "1469",
      "today_stars": "1 star today"
    },
    {
      "author": "dr5hn",
      "name": "countries-states-cities-database",
      "full_name": "dr5hn/countries-states-cities-database",
      "url": "https://github.com/dr5hn/countries-states-cities-database",
      "description": "🌍 Discover our global repository of countries, states, and cities! 🏙️ Get comprehensive data in JSON, SQL, PSQL, SQLSERVER, MONGODB, SQLITE, XML, YAML, and CSV formats. Access ISO2, ISO3 codes, country code, capital, native language, timezones (for countries), and more. #countries #states #cities",
      "language": "PHP",
      "stars": "8098",
      "forks": "2735",
      "today_stars": "4 stars today"
    },
    {
      "author": "dompdf",
      "name": "dompdf",
      "full_name": "dompdf/dompdf",
      "url": "https://github.com/dompdf/dompdf",
      "description": "HTML to PDF converter for PHP",
      "language": "PHP",
      "stars": "10757",
      "forks": "1809",
      "today_stars": "0 stars today"
    },
    {
      "author": "laravel",
      "name": "framework",
      "full_name": "laravel/framework",
      "url": "https://github.com/laravel/framework",
      "description": "The Laravel Framework.",
      "language": "PHP",
      "stars": "33438",
      "forks": "11284",
      "today_stars": "6 stars today"
    },
    {
      "author": "AzuraCast",
      "name": "AzuraCast",
      "full_name": "AzuraCast/AzuraCast",
      "url": "https://github.com/AzuraCast/AzuraCast",
      "description": "A self-hosted web radio management suite, including turnkey installer tools for the full radio software stack and a modern, easy-to-use web app to manage your stations.",
      "language": "PHP",
      "stars": "3343",
      "forks": "598",
      "today_stars": "6 stars today"
    },
    {
      "author": "PHPMailer",
      "name": "PHPMailer",
      "full_name": "PHPMailer/PHPMailer",
      "url": "https://github.com/PHPMailer/PHPMailer",
      "description": "The classic email sending library for PHP",
      "language": "PHP",
      "stars": "21381",
      "forks": "9783",
      "today_stars": "5 stars today"
    },
    {
      "author": "shlinkio",
      "name": "shlink",
      "full_name": "shlinkio/shlink",
      "url": "https://github.com/shlinkio/shlink",
      "description": "The definitive self-hosted URL shortener",
      "language": "PHP",
      "stars": "3762",
      "forks": "299",
      "today_stars": "2 stars today"
    }
  ]
}